Metadata-Version: 2.1
Name: sfjwt
Version: 1.0.1
Summary: A small repo to provide functions to authenticate against SalesForce.
Home-page: https://github.com/Rehket/SalesForceJWT-Server-Auth
Author: Adam A
Author-email: aalbright425@gmail.com
License: MIT
Platform: UNKNOWN
Provides-Extra: dev
